kumex/__init__.py
kumex/client.py
kumex/ws_client.py
kumex/base_request/__init__.py
kumex/base_request/base_request.py
kumex/marke_data/__init__.py
kumex/marke_data/market_data.py
kumex/trade/__init__.py
kumex/trade/trade.py
kumex/user/__init__.py
kumex/user/user.py
kumex/websocket/__init__.py
kumex/websocket/websocket.py
kumex/ws_token/__init__.py
kumex/ws_token/token.py
python_kumex-1.1.1.dist-info/LICENSE
python_kumex-1.1.1.dist-info/METADATA
python_kumex-1.1.1.dist-info/WHEEL
python_kumex-1.1.1.dist-info/top_level.txt
python_kumex-1.1.1.dist-info/RECORD
